mkdocs_pagelist_plugin/__init__.py
mkdocs_pagelist_plugin-0.2.2.dist-info/METADATA
mkdocs_pagelist_plugin-0.2.2.dist-info/WHEEL
mkdocs_pagelist_plugin-0.2.2.dist-info/entry_points.txt
mkdocs_pagelist_plugin-0.2.2.dist-info/top_level.txt
mkdocs_pagelist_plugin-0.2.2.dist-info/RECORD
