Metadata-Version: 2.1
Name: mkdocs-pagelist-plugin
Version: 0.2.2
Summary: A MkDocs plugin to list pages based on tags and folders
Home-page: https://github.com/alanpt/mkdocs-pagelist-plugin
Author: Alan Proctor-Thomson
Author-email: alanpt@gmail.com
License: MIT
Keywords: mkdocs python markdown pagelist
Requires-Dist: mkdocs >=1.0
